README.md
setup.cfg
setup.py
nomad_broker_cli/__init__.py
nomad_broker_cli/api_client.py
nomad_broker_cli/configuration.py
nomad_broker_cli/exceptions.py
nomad_broker_cli/model_utils.py
nomad_broker_cli/rest.py
nomad_broker_cli.egg-info/PKG-INFO
nomad_broker_cli.egg-info/SOURCES.txt
nomad_broker_cli.egg-info/dependency_links.txt
nomad_broker_cli.egg-info/requires.txt
nomad_broker_cli.egg-info/top_level.txt
nomad_broker_cli/api/__init__.py
nomad_broker_cli/api/customs_api.py
nomad_broker_cli/api/payment_api.py
nomad_broker_cli/api/payout_api.py
nomad_broker_cli/api/refund_api.py
nomad_broker_cli/api/settlement_api.py
nomad_broker_cli/apis/__init__.py
nomad_broker_cli/model/__init__.py
nomad_broker_cli/model/base_api_response.py
nomad_broker_cli/model/customs_code.py
nomad_broker_cli/model/customs_identification_request.py
nomad_broker_cli/model/customs_identification_response.py
nomad_broker_cli/model/customs_payment_order.py
nomad_broker_cli/model/customs_payment_redeclare_request.py
nomad_broker_cli/model/customs_payment_request.py
nomad_broker_cli/model/customs_payment_response.py
nomad_broker_cli/model/customs_payments_response.py
nomad_broker_cli/model/error_api_response.py
nomad_broker_cli/model/goods_info.py
nomad_broker_cli/model/payment_close_response.py
nomad_broker_cli/model/payment_detail_response.py
nomad_broker_cli/model/payment_invocation_request.py
nomad_broker_cli/model/payment_method.py
nomad_broker_cli/model/payment_product.py
nomad_broker_cli/model/payment_product_req.py
nomad_broker_cli/model/payment_request.py
nomad_broker_cli/model/payment_response.py
nomad_broker_cli/model/payment_type.py
nomad_broker_cli/model/payout_bill_request.py
nomad_broker_cli/model/payout_request.py
nomad_broker_cli/model/payout_request_express_info.py
nomad_broker_cli/model/payout_request_payee_info.py
nomad_broker_cli/model/payout_request_seller_info.py
nomad_broker_cli/model/payout_response.py
nomad_broker_cli/model/refund_account.py
nomad_broker_cli/model/refund_request.py
nomad_broker_cli/model/refund_response.py
nomad_broker_cli/model/settlement_receiver.py
nomad_broker_cli/model/settlement_receiver_request.py
