Metadata-Version: 2.1
Name: nomad-broker-cli
Version: 1.7.0
Summary: Nomad Broker
Home-page: UNKNOWN
Author: OpenAPI Generator community
Author-email: ben.song@samarkand.global
License: UNKNOWN
Keywords: OpenAPI,OpenAPI-Generator,Nomad Broker
Platform: UNKNOWN
Requires-Python: >=3.6
